ruconceptnet/__init__.py
ruconceptnet/conceptnet.py
ruconceptnet/meta.py
ruconceptnet/sparse_representation.py
ruconceptnet/data/__init__.py
ruconceptnet/data/russian-conceptnet.pickle.bz2
ruconceptnet-0.0.1.dist-info/LICENSE
ruconceptnet-0.0.1.dist-info/METADATA
ruconceptnet-0.0.1.dist-info/WHEEL
ruconceptnet-0.0.1.dist-info/top_level.txt
ruconceptnet-0.0.1.dist-info/RECORD
