Metadata-Version: 2.1
Name: ruconceptnet
Version: 0.0.1
Summary: Russian part of ConceptNet5.7 graph, fast access to relations.
Home-page: https://github.com/alexeyev/RussianConceptNet
Author: Anton Alekseev
Author-email: anton.m.alexeye@gmail.com
License: UNKNOWN
Keywords: nlp,knowledge graph,russian language
Platform: UNKNOWN
Classifier: Programming Language :: Python :: 3
Classifier: License :: OSI Approved :: MIT License
Classifier: Operating System :: OS Independent
Requires-Python: >=3.5
